{
  "n_seeds": 10,
  "seeds": [
    101,
    102,
    103,
    104,
    105,
    106,
    107,
    108,
    109,
    110
  ],
  "sigma_values": [
    0.0,
    0.1,
    0.25,
    0.5,
    1.0,
    2.0
  ],
  "per_seed_results": [
    {
      "seed": 101,
      "sigma_values": [
        0.0,
        0.1,
        0.25,
        0.5,
        1.0,
        2.0
      ],
      "rmse_values": [
        0.23190970276206296,
        0.32744127033118253,
        0.6318782482496084,
        1.1919101325348282,
        2.3062546955335814,
        4.531223251583169
      ]
    },
    {
      "seed": 102,
      "sigma_values": [
        0.0,
        0.1,
        0.25,
        0.5,
        1.0,
        2.0
      ],
      "rmse_values": [
        0.23493453264088943,
        0.33196681419333585,
        0.6160860635923516,
        1.191184376205734,
        2.4218225627849472,
        4.640373340768578
      ]
    },
    {
      "seed": 103,
      "sigma_values": [
        0.0,
        0.1,
        0.25,
        0.5,
        1.0,
        2.0
      ],
      "rmse_values": [
        0.22564853329158258,
        0.324719165405592,
        0.621810162342475,
        1.1615925433632257,
        2.3313461155888495,
        4.6292273719378
      ]
    },
    {
      "seed": 104,
      "sigma_values": [
        0.0,
        0.1,
        0.25,
        0.5,
        1.0,
        2.0
      ],
      "rmse_values": [
        0.22514120181927236,
        0.32455673159923326,
        0.604580198967944,
        1.1587753472364528,
        2.3565721747877384,
        4.5641426233674425
      ]
    },
    {
      "seed": 105,
      "sigma_values": [
        0.0,
        0.1,
        0.25,
        0.5,
        1.0,
        2.0
      ],
      "rmse_values": [
        0.22689995761828946,
        0.33645654527016944,
        0.6227832493458112,
        1.1605284117475851,
        2.309909638243295,
        4.759903009075257
      ]
    },
    {
      "seed": 106,
      "sigma_values": [
        0.0,
        0.1,
        0.25,
        0.5,
        1.0,
        2.0
      ],
      "rmse_values": [
        0.24239136850586968,
        0.3412138046116703,
        0.6317971299652118,
        1.1939345427859689,
        2.424817745906318,
        4.655959485482063
      ]
    },
    {
      "seed": 107,
      "sigma_values": [
        0.0,
        0.1,
        0.25,
        0.5,
        1.0,
        2.0
      ],
      "rmse_values": [
        0.22686767060835358,
        0.3179601782166477,
        0.6310845313037001,
        1.203581835009923,
        2.3673329517890784,
        4.534879016104488
      ]
    },
    {
      "seed": 108,
      "sigma_values": [
        0.0,
        0.1,
        0.25,
        0.5,
        1.0,
        2.0
      ],
      "rmse_values": [
        0.22722241653779948,
        0.3233036872565913,
        0.6159405848598999,
        1.1099425749433587,
        2.359487664016494,
        4.591510454003037
      ]
    },
    {
      "seed": 109,
      "sigma_values": [
        0.0,
        0.1,
        0.25,
        0.5,
        1.0,
        2.0
      ],
      "rmse_values": [
        0.23376171737486043,
        0.33760148483752184,
        0.6243965801001538,
        1.2192982735071403,
        2.347979571534632,
        4.652935604657965
      ]
    },
    {
      "seed": 110,
      "sigma_values": [
        0.0,
        0.1,
        0.25,
        0.5,
        1.0,
        2.0
      ],
      "rmse_values": [
        0.226736507966592,
        0.3226243173064591,
        0.6118627467084645,
        1.1627937669440587,
        2.2737804146204943,
        4.626225706392253
      ]
    }
  ]
}